rlgp/__init__.py
rlgp/version.py
rlgp-0.0.1.dist-info/LICENSE
rlgp-0.0.1.dist-info/METADATA
rlgp-0.0.1.dist-info/WHEEL
rlgp-0.0.1.dist-info/top_level.txt
rlgp-0.0.1.dist-info/RECORD
