Metadata-Version: 2.1
Name: rlgp
Version: 0.0.1
Summary: Graph Partitioning using Reinforcement Learning
Home-page: https://github.com/abdelrahmanhosny/RLGP
Author: Abdelrahman Hosny
Author-email: abdelrahman_hosny@brown.edu
License: BSD-3 License
Download-URL: https://github.com/abdelrahman/RLGP/archive/v_0.0.1.tar.gz
Keywords: Graph,Partitioning,Reinforcement,Learning
Platform: UNKNOWN
Classifier: Development Status :: 3 - Alpha
Classifier: Intended Audience :: Developers
Classifier: Topic :: Scientific/Engineering :: Electronic Design Automation (EDA)
Classifier: License :: OSI Approved :: BSD License
Classifier: Programming Language :: Python :: 3.7
